Lacmia/__init__.py
Lacmia/models/Lacmia.py
Lacmia/models/__init__.py
Lacmia/models/adam.py
Lacmia/models/decoder.py
Lacmia/models/encoder.py
Lacmia/models/generate.py
Lacmia/models/model_builder.py
Lacmia/models/neural.py
Lacmia/models/optimizers.py
Lacmia/models/predictor.py
Lacmia-1.0.1.dist-info/METADATA
Lacmia-1.0.1.dist-info/WHEEL
Lacmia-1.0.1.dist-info/top_level.txt
Lacmia-1.0.1.dist-info/RECORD
