Metadata-Version: 2.1
Name: Lacmia
Version: 1.0.1
Summary: Chinese Minority Abstractive Multi-language summarization project
Author: HaoYu Luo
Author-email: 506685820@qq.com
Classifier: Programming Language :: Python :: 3
Classifier: License :: OSI Approved :: MIT License
Classifier: Operating System :: OS Independent
Requires-Python: >=3.8
Requires-Dist: torch
Requires-Dist: numpy
Requires-Dist: tqdm
Requires-Dist: transformers
Requires-Dist: OpenNMT-py
